AISAPLibrary/AISAPLibrary.py
AISAPLibrary/__init__.py
AISAPLibrary/click_element_multithread.py
AISAPLibrary/send_vkey_multithread.py
AISAPLibrary-1.0.21.dist-info/METADATA
AISAPLibrary-1.0.21.dist-info/WHEEL
AISAPLibrary-1.0.21.dist-info/top_level.txt
AISAPLibrary-1.0.21.dist-info/RECORD
