Metadata-Version: 2.1
Name: AISAPLibrary
Version: 1.0.21
Summary: Modified Package For SapGuiLibrary
Author: Annas Wahyu Ramadhan
Classifier: Programming Language :: Python :: 3
Classifier: License :: OSI Approved :: MIT License
Classifier: Operating System :: OS Independent
Requires-Python: >=3.7
